hackyargparser/README.md
hackyargparser/__init__.py
hackyargparser/requirements.txt
hackyargparser/thirdparty.json
hackyargparser-0.12.dist-info/LICENSE.rst
hackyargparser-0.12.dist-info/METADATA
hackyargparser-0.12.dist-info/WHEEL
hackyargparser-0.12.dist-info/top_level.txt
hackyargparser-0.12.dist-info/RECORD
