Metadata-Version: 2.1
Name: hackyargparser
Version: 0.12
Summary: Hacky argparser - parses arguments and changes the defaults of functions
Home-page: https://github.com/hansalemaos/hackyargparser
Author: Johannes Fischer
Author-email: aulasparticularesdealemaosp@gmail.com
License: MIT
Keywords: argparser
Classifier: Development Status :: 4 - Beta
Classifier: Programming Language :: Python :: 3 :: Only
Classifier: Programming Language :: Python :: 3.10
Classifier: Topic :: Software Development :: Libraries :: Python Modules
Classifier: Topic :: Utilities
License-File: LICENSE.rst
